dynamic_scraper/__init__.py
dynamic_scraper/admin.py
dynamic_scraper/models.py
dynamic_scraper/pipelines.py
dynamic_scraper/views.py
dynamic_scraper/management/__init__.py
dynamic_scraper/management/commands/__init__.py
dynamic_scraper/management/commands/check_last_checker_deletes.py
dynamic_scraper/management/commands/check_last_scraper_saves.py
dynamic_scraper/management/commands/run_checker_tests.py
dynamic_scraper/migrations/0001_initial.py
dynamic_scraper/migrations/0002_scraper_render_javascript.py
dynamic_scraper/migrations/0003_auto_20150610_0906.py
dynamic_scraper/migrations/0004_scrapedobjattr_id_field.py
dynamic_scraper/migrations/0005_new_dict_params_for_scraper.py
dynamic_scraper/migrations/0006_request_type_and_body.py
dynamic_scraper/migrations/0007_dont_filter_attribute.py
dynamic_scraper/migrations/0008_new_request_page_types_construct.py
dynamic_scraper/migrations/0009_removed_legacy_request_page_type_scraper_fields.py
dynamic_scraper/migrations/0010_move_save_to_db_to_scraped_obj_attr.py
dynamic_scraper/migrations/0011_extracted_checker_attributes_to_own_checker_class.py
dynamic_scraper/migrations/0012_removed_legacy_checker_scraper_attributes.py
dynamic_scraper/migrations/0013_added_scraper_save_and_checker_delete_datetime_fields.py
dynamic_scraper/migrations/0014_added_scraper_save_and_checker_delete_alert_period_fields_for_scraper.py
dynamic_scraper/migrations/0015_added_datetime_fields_for_last_scraper_save_and_checker_delete_alert.py
dynamic_scraper/migrations/0016_optional_xpath_fields_text_type_for_x_path_reg_exp_processor_fields.py
dynamic_scraper/migrations/0017_added_order_to_scraped_obj_attr.py
dynamic_scraper/migrations/0018_added_use_default_procs_field_to_scraper_elems.py
dynamic_scraper/migrations/0019_updated_help_texts_for_request_info_fields.py
dynamic_scraper/migrations/0020_added_work_status_field_to_scraper.py
dynamic_scraper/migrations/0021_added_owner_field_to_scraper.py
django_dynamic_scraper-0.13.3.dist-info/LICENSE
django_dynamic_scraper-0.13.3.dist-info/METADATA
django_dynamic_scraper-0.13.3.dist-info/WHEEL
django_dynamic_scraper-0.13.3.dist-info/top_level.txt
django_dynamic_scraper-0.13.3.dist-info/RECORD
